cbm_runner/__init__.py
cbm_runner/all_countries.py
cbm_runner/runner.py
cbm_runner-0.2.0.dist-info/LICENSE.txt
cbm_runner-0.2.0.dist-info/METADATA
cbm_runner-0.2.0.dist-info/WHEEL
cbm_runner-0.2.0.dist-info/top_level.txt
cbm_runner-0.2.0.dist-info/RECORD
