Metadata-Version: 2.1
Name: cbm-runner
Version: 0.2.0
Summary: cbm_runner is a python package for running carbon budget simulations.
Home-page: UNKNOWN
Author: Lucas Sinclair
Author-email: lucas.sinclair@me.com
License: MIT
Platform: UNKNOWN
Requires-Dist: autopaths
Requires-Dist: plumbing
Requires-Dist: pymarktex
Requires-Dist: pbs
